invenio_pages/__init__.py
invenio_pages/config.py
invenio_pages/ext.py
invenio_pages/proxies.py
invenio_pages/views.py
invenio_pages/administration/__init__.py
invenio_pages/administration/views/__init__.py
invenio_pages/administration/views/pages.py
invenio_pages/alembic/08a5708005b7_change_datetime_types.py
invenio_pages/alembic/145402e8523a_create_pages_table.py
invenio_pages/alembic/1737449793_add_language_and_new_uq.py
invenio_pages/alembic/98e0a418340d_create_invenio_pages_branch.py
invenio_pages/alembic/9fae3c5404d9_remove_has_custom_view_to_pages.py
invenio_pages/alembic/__init__.py
invenio_pages/alembic/b0f93ca4a147_add_has_custom_view_to_pages.py
invenio_pages/records/__init__.py
invenio_pages/records/errors.py
invenio_pages/records/models.py
invenio_pages/resources/__init__.py
invenio_pages/resources/config.py
invenio_pages/resources/resource.py
invenio_pages/services/__init__.py
invenio_pages/services/config.py
invenio_pages/services/permissions.py
invenio_pages/services/results.py
invenio_pages/services/schemas.py
invenio_pages/services/service.py
invenio_pages/templates/invenio_pages/base.html
invenio_pages/templates/invenio_pages/default.html
invenio_pages/templates/invenio_pages/dynamic.html
invenio_pages/translations/messages.pot
invenio_pages/translations/ar/LC_MESSAGES/messages.mo
invenio_pages/translations/ar/LC_MESSAGES/messages.po
invenio_pages/translations/bg/LC_MESSAGES/messages.mo
invenio_pages/translations/bg/LC_MESSAGES/messages.po
invenio_pages/translations/ca/LC_MESSAGES/messages.mo
invenio_pages/translations/ca/LC_MESSAGES/messages.po
invenio_pages/translations/cs/LC_MESSAGES/messages.mo
invenio_pages/translations/cs/LC_MESSAGES/messages.po
invenio_pages/translations/da/LC_MESSAGES/messages.mo
invenio_pages/translations/da/LC_MESSAGES/messages.po
invenio_pages/translations/de/LC_MESSAGES/messages.mo
invenio_pages/translations/de/LC_MESSAGES/messages.po
invenio_pages/translations/el/LC_MESSAGES/messages.mo
invenio_pages-8.0.0.dist-info/licenses/AUTHORS.rst
invenio_pages-8.0.0.dist-info/licenses/LICENSE
invenio_pages-8.0.0.dist-info/METADATA
invenio_pages-8.0.0.dist-info/WHEEL
invenio_pages-8.0.0.dist-info/entry_points.txt
invenio_pages-8.0.0.dist-info/top_level.txt
invenio_pages-8.0.0.dist-info/RECORD
